Workbook

Sheet Overview
A1: Ticker | B1: Company | C1: Sector | D1: Industry | E1: Country | F1: Notes | G1: Simplicity (1-10) | H1: Operating History (1-10) | I1: Moat (1-10) | J1: Management (1-10) | K1: ROE/ROIC (1-10) | L1: Predictability (1-10) | M1: Capital Allocation (1-10) | N1: Leverage Prudence (1-10) | O1: Resilience (1-10) | P1: Price vs Value (1-10) | Q1: Total (0-100) | R1: Average (0-10) | S1: Rank
A2: =Tickers!A2 | B2: =Tickers!B2 | C2: =Tickers!F2 | D2: =Tickers!G2 | E2: =Tickers!H2 | G2: =Simplicity!$R$2 | H2: =OperatingHistory!$N$2 | I2: =Moat!$Q$2 | J2: =Management!$P$2 | K2: =ROE_ROIC!$J$2 | L2: =Predictability!$L$2 | M2: =CapitalAllocation!$L$2 | N2: =Leverage!$N$2 | O2: =Resilience!$O$2 | P2: =PriceValue!O2 | Q2: =SUM(G2:P2) | R2: =Q2/10 | S2: =RANK(R2,R$2:R$17,0)
A3: =Tickers!A3 | B3: =Tickers!B3 | C3: =Tickers!F3 | D3: =Tickers!G3 | E3: =Tickers!H3 | G3: =Simplicity!$R$3 | H3: =OperatingHistory!$N$3 | I3: =Moat!$Q$3 | J3: =Management!$P$3 | K3: =ROE_ROIC!$J$3 | L3: =Predictability!$L$3 | M3: =CapitalAllocation!$L$3 | N3: =Leverage!$N$3 | O3: =Resilience!$O$3 | P3: =PriceValue!O3 | Q3: =SUM(G3:P3) | R3: =Q3/10 | S3: =RANK(R3,R$2:R$17,0)
A4: =Tickers!A4 | B4: =Tickers!B4 | C4: =Tickers!F4 | D4: =Tickers!G4 | E4: =Tickers!H4 | G4: =Simplicity!$R$4 | H4: =OperatingHistory!$N$4 | I4: =Moat!$Q$4 | J4: =Management!$P$4 | K4: =ROE_ROIC!$J$4 | L4: =Predictability!$L$4 | M4: =CapitalAllocation!$L$4 | N4: =Leverage!$N$4 | O4: =Resilience!$O$4 | P4: =PriceValue!O4 | Q4: =SUM(G4:P4) | R4: =Q4/10 | S4: =RANK(R4,R$2:R$17,0)
A5: =Tickers!A5 | B5: =Tickers!B5 | C5: =Tickers!F5 | D5: =Tickers!G5 | E5: =Tickers!H5 | G5: =Simplicity!$R$5 | H5: =OperatingHistory!$N$5 | I5: =Moat!$Q$5 | J5: =Management!$P$5 | K5: =ROE_ROIC!$J$5 | L5: =Predictability!$L$5 | M5: =CapitalAllocation!$L$5 | N5: =Leverage!$N$5 | O5: =Resilience!$O$5 | P5: =PriceValue!O5 | Q5: =SUM(G5:P5) | R5: =Q5/10 | S5: =RANK(R5,R$2:R$17,0)
A6: =Tickers!A6 | B6: =Tickers!B6 | C6: =Tickers!F6 | D6: =Tickers!G6 | E6: =Tickers!H6 | G6: =Simplicity!$R$6 | H6: =OperatingHistory!$N$6 | I6: =Moat!$Q$6 | J6: =Management!$P$6 | K6: =ROE_ROIC!$J$6 | L6: =Predictability!$L$6 | M6: =CapitalAllocation!$L$6 | N6: =Leverage!$N$6 | O6: =Resilience!$O$6 | P6: =PriceValue!O6 | Q6: =SUM(G6:P6) | R6: =Q6/10 | S6: =RANK(R6,R$2:R$17,0)
A7: =Tickers!A7 | B7: =Tickers!B7 | C7: =Tickers!F7 | D7: =Tickers!G7 | E7: =Tickers!H7 | G7: =Simplicity!$R$7 | H7: =OperatingHistory!$N$7 | I7: =Moat!$Q$7 | J7: =Management!$P$7 | K7: =ROE_ROIC!$J$7 | L7: =Predictability!$L$7 | M7: =CapitalAllocation!$L$7 | N7: =Leverage!$N$7 | O7: =Resilience!$O$7 | P7: =PriceValue!O7 | Q7: =SUM(G7:P7) | R7: =Q7/10 | S7: =RANK(R7,R$2:R$17,0)
A8: =Tickers!A8 | B8: =Tickers!B8 | C8: =Tickers!F8 | D8: =Tickers!G8 | E8: =Tickers!H8 | G8: =Simplicity!$R$8 | H8: =OperatingHistory!$N$8 | I8: =Moat!$Q$8 | J8: =Management!$P$8 | K8: =ROE_ROIC!$J$8 | L8: =Predictability!$L$8 | M8: =CapitalAllocation!$L$8 | N8: =Leverage!$N$8 | O8: =Resilience!$O$8 | P8: =PriceValue!O8 | Q8: =SUM(G8:P8) | R8: =Q8/10 | S8: =RANK(R8,R$2:R$17,0)
A9: =Tickers!A9 | B9: =Tickers!B9 | C9: =Tickers!F9 | D9: =Tickers!G9 | E9: =Tickers!H9 | G9: =Simplicity!$R$9 | H9: =OperatingHistory!$N$9 | I9: =Moat!$Q$9 | J9: =Management!$P$9 | K9: =ROE_ROIC!$J$9 | L9: =Predictability!$L$9 | M9: =CapitalAllocation!$L$9 | N9: =Leverage!$N$9 | O9: =Resilience!$O$9 | P9: =PriceValue!O9 | Q9: =SUM(G9:P9) | R9: =Q9/10 | S9: =RANK(R9,R$2:R$17,0)
A10: =Tickers!A10 | B10: =Tickers!B10 | C10: =Tickers!F10 | D10: =Tickers!G10 | E10: =Tickers!H10 | G10: =Simplicity!$R$10 | H10: =OperatingHistory!$N$10 | I10: =Moat!$Q$10 | J10: =Management!$P$10 | K10: =ROE_ROIC!$J$10 | L10: =Predictability!$L$10 | M10: =CapitalAllocation!$L$10 | N10: =Leverage!$N$10 | O10: =Resilience!$O$10 | P10: =PriceValue!O10 | Q10: =SUM(G10:P10) | R10: =Q10/10 | S10: =RANK(R10,R$2:R$17,0)
A11: =Tickers!A11 | B11: =Tickers!B11 | C11: =Tickers!F11 | D11: =Tickers!G11 | E11: =Tickers!H11 | G11: =Simplicity!$R$11 | H11: =OperatingHistory!$N$11 | I11: =Moat!$Q$11 | J11: =Management!$P$11 | K11: =ROE_ROIC!$J$11 | L11: =Predictability!$L$11 | M11: =CapitalAllocation!$L$11 | N11: =Leverage!$N$11 | O11: =Resilience!$O$11 | P11: =PriceValue!O11 | Q11: =SUM(G11:P11) | R11: =Q11/10 | S11: =RANK(R11,R$2:R$17,0)
A12: =Tickers!A12 | B12: =Tickers!B12 | C12: =Tickers!F12 | D12: =Tickers!G12 | E12: =Tickers!H12 | G12: =Simplicity!$R$12 | H12: =OperatingHistory!$N$12 | I12: =Moat!$Q$12 | J12: =Management!$P$12 | K12: =ROE_ROIC!$J$12 | L12: =Predictability!$L$12 | M12: =CapitalAllocation!$L$12 | N12: =Leverage!$N$12 | O12: =Resilience!$O$12 | P12: =PriceValue!O12 | Q12: =SUM(G12:P12) | R12: =Q12/10 | S12: =RANK(R12,R$2:R$17,0)
A13: =Tickers!A13 | B13: =Tickers!B13 | C13: =Tickers!F13 | D13: =Tickers!G13 | E13: =Tickers!H13 | G13: =Simplicity!$R$13 | H13: =OperatingHistory!$N$13 | I13: =Moat!$Q$13 | J13: =Management!$P$13 | K13: =ROE_ROIC!$J$13 | L13: =Predictability!$L$13 | M13: =CapitalAllocation!$L$13 | N13: =Leverage!$N$13 | O13: =Resilience!$O$13 | P13: =PriceValue!O13 | Q13: =SUM(G13:P13) | R13: =Q13/10 | S13: =RANK(R13,R$2:R$17,0)
A14: =Tickers!A14 | B14: =Tickers!B14 | C14: =Tickers!F14 | D14: =Tickers!G14 | E14: =Tickers!H14 | G14: =Simplicity!$R$14 | H14: =OperatingHistory!$N$14 | I14: =Moat!$Q$14 | J14: =Management!$P$14 | K14: =ROE_ROIC!$J$14 | L14: =Predictability!$L$14 | M14: =CapitalAllocation!$L$14 | N14: =Leverage!$N$14 | O14: =Resilience!$O$14 | P14: =PriceValue!O14 | Q14: =SUM(G14:P14) | R14: =Q14/10 | S14: =RANK(R14,R$2:R$17,0)
A15: =Tickers!A15 | B15: =Tickers!B15 | C15: =Tickers!F15 | D15: =Tickers!G15 | E15: =Tickers!H15 | G15: =Simplicity!$R$15 | H15: =OperatingHistory!$N$15 | I15: =Moat!$Q$15 | J15: =Management!$P$15 | K15: =ROE_ROIC!$J$15 | L15: =Predictability!$L$15 | M15: =CapitalAllocation!$L$15 | N15: =Leverage!$N$15 | O15: =Resilience!$O$15 | P15: =PriceValue!O15 | Q15: =SUM(G15:P15) | R15: =Q15/10 | S15: =RANK(R15,R$2:R$17,0)
A16: =Tickers!A16 | B16: =Tickers!B16 | C16: =Tickers!F16 | D16: =Tickers!G16 | E16: =Tickers!H16 | G16: =Simplicity!$R$16 | H16: =OperatingHistory!$N$16 | I16: =Moat!$Q$16 | J16: =Management!$P$16 | K16: =ROE_ROIC!$J$16 | L16: =Predictability!$L$16 | M16: =CapitalAllocation!$L$16 | N16: =Leverage!$N$16 | O16: =Resilience!$O$16 | P16: =PriceValue!O16 | Q16: =SUM(G16:P16) | R16: =Q16/10 | S16: =RANK(R16,R$2:R$17,0)
A17: =Tickers!A17 | B17: =Tickers!B17 | C17: =Tickers!F17 | D17: =Tickers!G17 | E17: =Tickers!H17 | G17: =Simplicity!$R$17 | H17: =OperatingHistory!$N$17 | I17: =Moat!$Q$17 | J17: =Management!$P$17 | K17: =ROE_ROIC!$J$17 | L17: =Predictability!$L$17 | M17: =CapitalAllocation!$L$17 | N17: =Leverage!$N$17 | O17: =Resilience!$O$17 | P17: =PriceValue!O17 | Q17: =SUM(G17:P17) | R17: =Q17/10 | S17: =RANK(R17,R$2:R$17,0)
Q18: =SUM(G18:P18) | R18: =Q18/10 | S18: =RANK(R18,R$2:R$201,0)
Q19: =SUM(G19:P19) | R19: =Q19/10 | S19: =RANK(R19,R$2:R$201,0)
Q20: =SUM(G20:P20) | R20: =Q20/10 | S20: =RANK(R20,R$2:R$201,0)
Q21: =SUM(G21:P21) | R21: =Q21/10 | S21: =RANK(R21,R$2:R$201,0)
Q22: =SUM(G22:P22) | R22: =Q22/10 | S22: =RANK(R22,R$2:R$201,0)
Q23: =SUM(G23:P23) | R23: =Q23/10 | S23: =RANK(R23,R$2:R$201,0)
Q24: =SUM(G24:P24) | R24: =Q24/10 | S24: =RANK(R24,R$2:R$201,0)
Q25: =SUM(G25:P25) | R25: =Q25/10 | S25: =RANK(R25,R$2:R$201,0)
Q26: =SUM(G26:P26) | R26: =Q26/10 | S26: =RANK(R26,R$2:R$201,0)
Q27: =SUM(G27:P27) | R27: =Q27/10 | S27: =RANK(R27,R$2:R$201,0)
Q28: =SUM(G28:P28) | R28: =Q28/10 | S28: =RANK(R28,R$2:R$201,0)
Q29: =SUM(G29:P29) | R29: =Q29/10 | S29: =RANK(R29,R$2:R$201,0)
... Q201: =SUM(G201:P201) | R201: =Q201/10 | S201: =RANK(R201,R$2:R$201,0)

Sheet Tickers
A1: Ticker | B1: Company | C1: ISIN | D1: CIK | E1: Exchange | F1: Sector | G1: Industry | H1: Country | I1: Currency | J1: Primary Source (Yahoo/SEC/M*) | K1: Include? (Y/N)
A2: WLK | B2: Westlake Corporation | C2: - | E2: NYQ | F2: Basic Materials | G2: Specialty Chemicals | H2: United States | I2: USD
A3: ARW | B3: Arrow Electronics, Inc. | C3: US0427351004 | E3: NYQ | F3: Technology | G3: Electronics & Computer Distribution | H3: United States | I3: USD
A4: TSN | B4: Tyson Foods, Inc. | C4: US9024941034 | E4: NYQ | F4: Consumer Defensive | G4: Farm Products | H4: United States | I4: USD
A5: BIIB | B5: Biogen Inc. | C5: US09062X1037 | E5: NMS | F5: Healthcare | G5: Drug Manufacturers - General | H5: United States | I5: USD
A6: DD | B6: DuPont de Nemours, Inc. | C6: - | E6: NYQ | F6: Basic Materials | G6: Specialty Chemicals | H6: United States | I6: USD
A7: ELV | B7: Elevance Health, Inc. | C7: US0367521038 | E7: NYQ | F7: Healthcare | G7: Healthcare Plans | H7: United States | I7: USD
A8: KMX | B8: CarMax, Inc. | C8: US1431301027 | E8: NYQ | F8: Consumer Cyclical | G8: Auto & Truck Dealerships | H8: United States | I8: USD
A9: HUM | B9: Humana Inc. | C9: US4448591028 | E9: NYQ | F9: Healthcare | G9: Healthcare Plans | H9: United States | I9: USD
A10: MOH | B10: Molina Healthcare, Inc. | C10: - | E10: NYQ | F10: Healthcare | G10: Healthcare Plans | H10: United States | I10: USD
A11: INTC | B11: Intel Corporation | C11: CNE100000G29 | E11: NMS | F11: Technology | G11: Semiconductors | H11: United States | I11: USD
A12: GOOG | B12: Alphabet Inc. | C12: CA02080M1005 | E12: NMS | F12: Communication Services | G12: Internet Content & Information | H12: United States | I12: USD
A13: AMZN | B13: Amazon.com, Inc. | C13: - | E13: NMS | F13: Consumer Cyclical | G13: Internet Retail | H13: United States | I13: USD
... A17: AAPL | B17: Apple Inc. | C17: US0378331005 | E17: NMS | F17: Technology | G17: Consumer Electronics | H17: United States | I17: USD

Sheet Simplicity
A1: Ticker | B1: Company | C1: Segment Count | D1: Segments (List) | E1: Rev by Top Segment (%) | F1: Rev by Top 2 Segments (%) | G1: Geographic Count | H1: Top Geography (%) | I1: Business Model (one-liner) | J1: Complexity Flags (Derivatives/Regs/Banking/Insurance) | K1: Accounting Complexity (Y/N) | L1: Off-Balance Exposures (Y/N) | M1: Products (Few/Many) | N1: Customers (Concentrated/Fragmented) | O1: Supplier Concentration (Y/N) | P1: Channel Complexity (Y/N) | Q1: Notes | R1: Score (1-10) | S1: Source | T1: Last Updated

Sheet OperatingHistory
A1: Ticker | B1: Company | C1: Founded Year | D1: IPO Year | E1: Years Since IPO | F1: Years of Profitability (last 10) | G1: Revenue 10Y CAGR (%) | H1: EPS 10Y CAGR (%) | I1: Rev Down Years (10Y) | J1: EPS Down Years (10Y) | K1: Restatements (Y/N) | L1: Major Strategy Pivots (Y/N) | M1: Notes | N1: Score (1-10) | O1: Source | P1: Last Updated

Sheet Moat
A1: Ticker | B1: Company | C1: Moat Type (Brand/Cost/Switching/Network/Regulatory) | D1: 5Y Avg ROE (%) | E1: 5Y Avg ROIC (%) | F1: 5Y Avg Gross Margin (%) | G1: 5Y Avg Operating Margin (%) | H1: Market Share (%) | I1: Market Share Trend (Up/Flat/Down) | J1: Pricing Power Evidence (Y/N) | K1: Patents/IP (Y/N) | L1: High Switching Costs (Y/N) | M1: Cost Advantage (Y/N) | N1: Network Effects (Y/N) | O1: Reg/License Moat (Y/N) | P1: Notes | Q1: Score (1-10) | R1: Source | S1: Last Updated

Sheet Management
A1: Ticker | B1: Company | C1: CEO Tenure (yrs) | D1: CFO Tenure (yrs) | E1: Insider Ownership (%) | F1: Compensation Alignment (ROIC/EPS/FCF?) | G1: Capital Allocation Letters (Y/N) | H1: Disclosure Quality (High/Med/Low) | I1: Related-Party Risks (Y/N) | J1: Accounting Conservatism (High/Med/Low) | K1: Share Count 5Y Change (%) | L1: Buybacks Below IV? (Y/N) | M1: M&A Discipline (Good/Mixed/Poor) | N1: Dividend Policy (None/Steady/Growing/Cut) | O1: Notes | P1: Score (1-10) | Q1: Source | R1: Last Updated

Sheet ROE_ROIC
A1: Ticker | B1: Company | C1: ROE TTM (%) | D1: ROE 5Y Avg (%) | E1: ROIC TTM (%) | F1: ROIC 5Y Avg (%) | G1: FCF Margin 5Y Avg (%) | H1: CapEx/Sales 5Y Avg (%) | I1: Notes | J1: Score (1-10) | K1: Source | L1: Last Updated

Sheet Predictability
A1: Ticker | B1: Company | C1: EPS 10Y StdDev | D1: EPS 10Y CAGR (%) | E1: Operating Margin 10Y Avg (%) | F1: Operating Margin 10Y StdDev | G1: Revenue 10Y StdDev | H1: Gross Margin Stability (High/Med/Low) | I1: Earnings Drawdown (Worst %) | J1: Guidance Accuracy (High/Med/Low) | K1: Notes | L1: Score (1-10) | M1: Source | N1: Last Updated

Sheet CapitalAllocation
A1: Ticker | B1: Company | C1: Shares Outstanding 5Y Δ (%) | D1: Net Buyback Yield (5Y Avg %) | E1: Dividend Payout Ratio 5Y Avg (%) | F1: Reinvestment Rate (FCF->CapEx/R&D %) | G1: Acquisition Spend 5Y (USD) | H1: Post-M&A ROIC (Est %) | I1: Debt Issuance vs FCF (5Y) | J1: Specials/One-offs (Y/N) | K1: Notes | L1: Score (1-10) | M1: Source | N1: Last Updated

Sheet Leverage
A1: Ticker | B1: Company | C1: Debt/Equity (TTM) | D1: Debt/Equity 5Y Avg | E1: Interest Coverage (EBIT/Int) | F1: Net Debt / EBITDA | G1: Cash & Equivalents (USD) | H1: Debt Maturity <2Y (USD) | I1: Debt Maturity 2–5Y (USD) | J1: Debt Maturity >5Y (USD) | K1: Liquidity Facilities (Y/N) | L1: Covenant Headroom (Y/N) | M1: Notes | N1: Score (1-10) | O1: Source | P1: Last Updated

Sheet Resilience
A1: Ticker | B1: Company | C1: Beta (5Y) | D1: Demand Type (Recurring/Discretionary) | E1: Op Margin 10Y StdDev | F1: Revenue Change in 2008-09 (%) | G1: Revenue Change in 2020 (%) | H1: EPS Change in 2008-09 (%) | I1: EPS Change in 2020 (%) | J1: Dividend Cuts in Crises (Y/N) | K1: Customer Diversification (High/Med/Low) | L1: Supply Chain Risk (High/Med/Low) | M1: Regulatory Sensitivity (High/Med/Low) | N1: Notes | O1: Score (1-10) | P1: Source | Q1: Last Updated

Sheet PriceValue
A1: Ticker | B1: Company | C1: P/E (TTM) | D1: P/E 10Y Median | E1: P/B (MRQ) | F1: P/B 10Y Median | G1: EV/EBIT (TTM) | H1: EV/EBIT 10Y Median | I1: P/FCF (TTM) | J1: P/FCF 10Y Median | K1: Yield vs 10Y UST (bps) | L1: Implied IV Discount (%) | M1: Alt Fair Value (Morningstar/Guru) | N1: Notes | O1: Score (1-10) | P1: Source | Q1: Last Updated

Sheet Sources
A1: Source Name | B1: URL or API | C1: Coverage (Which fields) | D1: Latency (Daily/Quarterly) | E1: License/Notes

Sheet DataDictionary
A1: Field | B1: Definition | C1: Units/Format | D1: Example | E1: Preferred Source | F1: Fallback Source

Sheet Instructions
A1: Buffett Qualitative Data Model — How to use
A3: 1) Fill 'Tickers' first (set Include?=Y for covered tickers).
A4: 2) For each criterion sheet, fill rows for your tickers with the fields listed.
A5: 3) Enter a 1–10 'Score' in each criterion sheet (or compute later with a script).
A6: 4) In 'Overview', paste Ticker/Company and the ten scores; totals and rank auto-calc.
A7: 5) Use 'Sources' to track where each field came from; 'DataDictionary' to define fields.
A8: Tip: Keep 'Source' and 'Last Updated' filled on every row for auditability.
